schemata/__init__.py
schemata/exporters.py
schemata/parser.py
schemata/structures.py
schematacode-1.0.1.dist-info/LICENSE
schematacode-1.0.1.dist-info/METADATA
schematacode-1.0.1.dist-info/WHEEL
schematacode-1.0.1.dist-info/top_level.txt
schematacode-1.0.1.dist-info/RECORD
