Metadata-Version: 2.1
Name: schematacode
Version: 1.0.1
Summary: Schemata is a file format that makes writing XML and JSON schemas easier.
Home-page: https://github.com/SchemataCode/Schemata
Author: B. T. Milnes
License: UNKNOWN
Platform: UNKNOWN
License-File: LICENSE
